{"nom":"Monfort","circ":"2ème circonscription","dpt":"Gers","inscrits":372,"abs":142,"votants":230,"blancs":12,"nuls":2,"exp":216,"res":[{"nuance":"REM","nom":"M. Christopher SOCCIO","voix":51},{"nuance":"SOC","nom":"Mme Gisèle BIÉMOURET","voix":44},{"nuance":"LR","nom":"Mme Barbara NETO","voix":25},{"nuance":"FI","nom":"Mme Myriam RIMBERT","voix":20},{"nuance":"DVD","nom":"M. Michel GABAS","voix":19},{"nuance":"FN","nom":"M. Thomas GUASCH","voix":18},{"nuance":"DVG","nom":"M. Jean-Luc DAVEZAC","voix":14},{"nuance":"COM","nom":"M. Bruno GABRIEL","voix":7},{"nuance":"DLF","nom":"M. Bruno DIENOT","voix":6},{"nuance":"DVG","nom":"M. Franck WALTER","voix":3},{"nuance":"DIV","nom":"Mme Suzanne VIVANT","voix":3},{"nuance":"ECO","nom":"M. Jean-Paul DUGOUJON","voix":2},{"nuance":"EXG","nom":"Mme Michèle MARTIN","voix":1},{"nuance":"DVD","nom":"Mme Jacqueline DENEUVE","voix":1},{"nuance":"DIV","nom":"M. Cédric DAVANT","voix":1},{"nuance":"DIV","nom":"M. Jérémy COLLOT","voix":1}]}