{"nom":"Bergères-lès-Vertus","circ":"5ème circonscription","dpt":"Marne","inscrits":514,"abs":312,"votants":202,"blancs":5,"nuls":0,"exp":197,"res":[{"nuance":"UDI","nom":"M. Charles DE COURSON","voix":99},{"nuance":"REM","nom":"M. Bertrand TREPO","voix":43},{"nuance":"FN","nom":"M. Thomas LAVAL","voix":38},{"nuance":"DLF","nom":"Mme Estelle ARBOGAST","voix":6},{"nuance":"EXG","nom":"Mme Joëlle BASTIEN","voix":4},{"nuance":"FI","nom":"Mme Laurène MASSICARD","voix":3},{"nuance":"COM","nom":"Mme Dominique CHAILLOUX","voix":2},{"nuance":"ECO","nom":"Mme Françoise DEHUT","voix":1},{"nuance":"DIV","nom":"M. Naceur YAGOUBI","voix":1},{"nuance":"EXD","nom":"M. Julien HAVASI","voix":0}]}