{"nom":"Bréban","circ":"5ème circonscription","dpt":"Marne","inscrits":83,"abs":35,"votants":48,"blancs":1,"nuls":0,"exp":47,"res":[{"nuance":"UDI","nom":"M. Charles DE COURSON","voix":30},{"nuance":"FN","nom":"M. Thomas LAVAL","voix":9},{"nuance":"REM","nom":"M. Bertrand TREPO","voix":5},{"nuance":"FI","nom":"Mme Laurène MASSICARD","voix":2},{"nuance":"ECO","nom":"Mme Françoise DEHUT","voix":1},{"nuance":"EXG","nom":"Mme Joëlle BASTIEN","voix":0},{"nuance":"COM","nom":"Mme Dominique CHAILLOUX","voix":0},{"nuance":"DIV","nom":"M. Naceur YAGOUBI","voix":0},{"nuance":"DLF","nom":"Mme Estelle ARBOGAST","voix":0},{"nuance":"EXD","nom":"M. Julien HAVASI","voix":0}]}