{"nom":"Argenton-Notre-Dame","circ":"2ème circonscription","dpt":"Mayenne","inscrits":145,"abs":45,"votants":100,"blancs":0,"nuls":1,"exp":99,"res":[{"nuance":"LR","nom":"M. Guillaume CHEVROLLIER","voix":33},{"nuance":"MDM","nom":"Mme Géraldine BANNIER","voix":32},{"nuance":"FN","nom":"Mme Sylviane DÉGÉ","voix":12},{"nuance":"SOC","nom":"Mme Marie-Noëlle TRIBONDEAU","voix":10},{"nuance":"FI","nom":"Mme Emeline RIO","voix":4},{"nuance":"DLF","nom":"Mme Françoise CHIVERT","voix":3},{"nuance":"COM","nom":"M. Florian DEROUET","voix":2},{"nuance":"DIV","nom":"M. Martin BORDEAU","voix":1},{"nuance":"EXG","nom":"Mme Maryse LÉPRON","voix":1},{"nuance":"EXD","nom":"Mme Marie DE PONFILLY","voix":1},{"nuance":"DIV","nom":"M. Joseph GAUDIN","voix":0},{"nuance":"ECO","nom":"Mme Françoise MARCHAND","voix":0}]}