{"nom":"Coullemont","circ":"1ère circonscription","dpt":"Pas-de-Calais","inscrits":94,"abs":38,"votants":56,"blancs":1,"nuls":1,"exp":54,"res":[{"nuance":"SOC","nom":"M. Jean-Jacques COTTEL","voix":21},{"nuance":"FN","nom":"Mme Agnès CAUDRON","voix":10},{"nuance":"FI","nom":"M. Gabriel BERTEIN","voix":7},{"nuance":"MDM","nom":"M. Bruno DUVERGÉ","voix":7},{"nuance":"LR","nom":"M. Michel PETIT","voix":4},{"nuance":"DLF","nom":"M. Arnaud CUGIER","voix":2},{"nuance":"DIV","nom":"Mme Carine BRABANT","voix":1},{"nuance":"ECO","nom":"Mme Sylvie JONIAUX","voix":1},{"nuance":"EXG","nom":"M. Jean-Paul WALLARD","voix":1},{"nuance":"EXG","nom":"M. Jérémy LAUTOUR","voix":0},{"nuance":"DVD","nom":"M. Mickaël DECOTTIGNIES","voix":0},{"nuance":"COM","nom":"Mme Maryse MASSART","voix":0},{"nuance":"DVG","nom":"M. Jean-Marie MONKA OCTAVE","voix":0},{"nuance":"EXD","nom":"M. Jean-Marc MAURICE","voix":0}]}