{"nom":"Marquise","circ":"6ème circonscription","dpt":"Pas-de-Calais","inscrits":3782,"abs":1892,"votants":1890,"blancs":26,"nuls":10,"exp":1854,"res":[{"nuance":"REM","nom":"Mme Brigitte BOURGUIGNON","voix":864},{"nuance":"FN","nom":"Mme Marie-Christine BOURGEOIS","voix":398},{"nuance":"FI","nom":"Mme Nadine DEMAREY","voix":255},{"nuance":"LR","nom":"M. Jean-Michel TACCOEN","voix":182},{"nuance":"DLF","nom":"Mme Claudine BLAUWART","voix":44},{"nuance":"COM","nom":"Mme Patricia DUVIEUBOURG","voix":39},{"nuance":"ECO","nom":"Mme Charlotte TALPAERT","voix":37},{"nuance":"EXG","nom":"Mme Valérie LEGRAND","voix":20},{"nuance":"DIV","nom":"Mme Florence DENIMAL","voix":15}]}