{"nom":"Diéval","circ":"1ère circonscription","dpt":"Pas-de-Calais","inscrits":575,"abs":289,"votants":286,"blancs":4,"nuls":0,"exp":282,"res":[{"nuance":"FN","nom":"Mme Agnès CAUDRON","voix":69},{"nuance":"MDM","nom":"M. Bruno DUVERGÉ","voix":65},{"nuance":"FI","nom":"M. Gabriel BERTEIN","voix":44},{"nuance":"LR","nom":"M. Michel PETIT","voix":38},{"nuance":"SOC","nom":"M. Jean-Jacques COTTEL","voix":32},{"nuance":"ECO","nom":"Mme Sylvie JONIAUX","voix":12},{"nuance":"DLF","nom":"M. Arnaud CUGIER","voix":8},{"nuance":"EXG","nom":"M. Jean-Paul WALLARD","voix":5},{"nuance":"COM","nom":"Mme Maryse MASSART","voix":4},{"nuance":"DIV","nom":"Mme Carine BRABANT","voix":2},{"nuance":"EXG","nom":"M. Jérémy LAUTOUR","voix":1},{"nuance":"DVG","nom":"M. Jean-Marie MONKA OCTAVE","voix":1},{"nuance":"EXD","nom":"M. Jean-Marc MAURICE","voix":1},{"nuance":"DVD","nom":"M. Mickaël DECOTTIGNIES","voix":0}]}