{"nom":"Bonningues-lès-Calais","circ":"7ème circonscription","dpt":"Pas-de-Calais","inscrits":466,"abs":163,"votants":303,"blancs":1,"nuls":8,"exp":294,"res":[{"nuance":"MDM","nom":"Mme Dominique PIEDFORT","voix":92},{"nuance":"LR","nom":"M. Pierre-Henri DUMONT","voix":56},{"nuance":"SOC","nom":"M. Yann CAPET","voix":51},{"nuance":"FN","nom":"M. Philippe OLIVIER","voix":43},{"nuance":"FI","nom":"Mme Anne-Sophie LIGNIERT","voix":24},{"nuance":"DLF","nom":"M. Sébastien LECOUSTRE","voix":12},{"nuance":"ECO","nom":"M. Francis GEST","voix":11},{"nuance":"EXG","nom":"Mme Isabelle FATOUX","voix":2},{"nuance":"COM","nom":"M. Jacky HENIN","voix":2},{"nuance":"DIV","nom":"Mme Janick CHARLET","voix":1},{"nuance":"EXG","nom":"Mme Françoise MILLOT","voix":0},{"nuance":"EXD","nom":"Mme Marie-Jeanne VINCENT","voix":0}]}