{"nom":"Antrenas","circ":"1ère circonscription","dpt":"Lozère","inscrits":242,"abs":104,"votants":138,"blancs":3,"nuls":4,"exp":131,"res":[{"nuance":"LR","nom":"M. Pierre MOREL A L'HUISSIER","voix":54},{"nuance":"REM","nom":"M. Francis PALOMBI","voix":23},{"nuance":"SOC","nom":"Mme Aurélie MAILLOLS","voix":19},{"nuance":"FN","nom":"M. Emmanuel GERSTNER","voix":9},{"nuance":"COM","nom":"M. Serge GAYSSOT","voix":8},{"nuance":"DVD","nom":"M. Regis TURC","voix":8},{"nuance":"FI","nom":"M. Christian CAUSSE","voix":6},{"nuance":"DLF","nom":"M. Loïc MARCHAND","voix":2},{"nuance":"DIV","nom":"Mme Marie-Hélène DUPY","voix":1},{"nuance":"EXG","nom":"Mme Annie SOUCHON","voix":1},{"nuance":"DIV","nom":"Mme Edith PARADIS","voix":0},{"nuance":"EXD","nom":"M. Frédéric DELPLACE","voix":0}]}