{"nom":"La Motte","circ":"8ème circonscription","dpt":"Var","inscrits":2396,"abs":1301,"votants":1095,"blancs":16,"nuls":5,"exp":1074,"res":[{"nuance":"REM","nom":"M. Fabien MATRAS","voix":372},{"nuance":"FN","nom":"M. Pierre JUGY","voix":257},{"nuance":"LR","nom":"M. Olivier AUDIBERT-TROIN","voix":241},{"nuance":"FI","nom":"Mme Patricia MASSIS-CALLET","voix":83},{"nuance":"ECO","nom":"M. Bruno DELPORT","voix":35},{"nuance":"DVD","nom":"Mme Clémence RAZEAU","voix":25},{"nuance":"DLF","nom":"M. Bernard LEMAITRE","voix":22},{"nuance":"COM","nom":"Mme Marie-Pierre BURLANDO","voix":13},{"nuance":"ECO","nom":"Mme Sophie GOY","voix":11},{"nuance":"DIV","nom":"M. Guy FERNANDEZ","voix":11},{"nuance":"EXG","nom":"M. Ludovic MARTIN","voix":4}]}