{"nom":"Méounes-lès-Montrieux","circ":"6ème circonscription","dpt":"Var","inscrits":1660,"abs":895,"votants":765,"blancs":11,"nuls":1,"exp":753,"res":[{"nuance":"REM","nom":"Mme Valérie GOMEZ-BASSAC","voix":270},{"nuance":"FN","nom":"M. Jérôme RIVIERE","voix":223},{"nuance":"LR","nom":"M. Marc LAURIOL","voix":115},{"nuance":"FI","nom":"Mme Jill CAZICONSTANTINOS","voix":56},{"nuance":"SOC","nom":"Mme Cécile LAUBLET","voix":18},{"nuance":"DVD","nom":"Mme Maryse RÉTALI","voix":15},{"nuance":"REG","nom":"M. Didier CADE","voix":11},{"nuance":"COM","nom":"M. Laurent CARRATALA","voix":10},{"nuance":"DIV","nom":"M. Cédric CARASCO","voix":9},{"nuance":"ECO","nom":"Mme Hélène LION","voix":7},{"nuance":"EXD","nom":"M. Gilles FOURNEL","voix":7},{"nuance":"RDG","nom":"M. Marc D'AMATO","voix":7},{"nuance":"EXD","nom":"M. Laurent LOPEZ","voix":5},{"nuance":"DVD","nom":"M. Frédéric WEBER","voix":0},{"nuance":"EXG","nom":"Mme Hélène DELAGE","voix":0}]}