{"nom":"Saint-Jacques-d'Aliermont","circ":"6ème circonscription","dpt":"Seine-Maritime","inscrits":271,"abs":119,"votants":152,"blancs":4,"nuls":1,"exp":147,"res":[{"nuance":"FN","nom":"M. Nicolas BAY","voix":45},{"nuance":"REM","nom":"M. Philippe DUFOUR","voix":39},{"nuance":"UDI","nom":"Mme Blandine LEFEBVRE","voix":31},{"nuance":"COM","nom":"M. Sébastien JUMEL","voix":27},{"nuance":"SOC","nom":"Mme Marie LE VERN","voix":3},{"nuance":"EXG","nom":"M. Éric MOISAN","voix":2},{"nuance":"DVG","nom":"M. Michel CORDIN","voix":0},{"nuance":"DIV","nom":"M. David GROUT","voix":0}]}