{"nom":"Ecalles-Alix","circ":"5ème circonscription","dpt":"Seine-Maritime","inscrits":436,"abs":210,"votants":226,"blancs":4,"nuls":2,"exp":220,"res":[{"nuance":"SOC","nom":"M. Christophe BOUILLON","voix":71},{"nuance":"FN","nom":"Mme Bénédicte LE MOËL","voix":53},{"nuance":"FI","nom":"Mme Myriam MULOT","voix":40},{"nuance":"LR","nom":"M. Jean DELALANDRE","voix":34},{"nuance":"ECO","nom":"M. Christophe MANCHON","voix":13},{"nuance":"DIV","nom":"M. Jean-Christophe LOUTRE","voix":5},{"nuance":"EXG","nom":"M. Simon SULKOWSKI","voix":2},{"nuance":"DVG","nom":"M. Benoît MARTIN","voix":2}]}