{"nom":"Bailly-en-Rivière","circ":"6ème circonscription","dpt":"Seine-Maritime","inscrits":392,"abs":195,"votants":197,"blancs":8,"nuls":0,"exp":189,"res":[{"nuance":"FN","nom":"M. Nicolas BAY","voix":69},{"nuance":"REM","nom":"M. Philippe DUFOUR","voix":46},{"nuance":"UDI","nom":"Mme Blandine LEFEBVRE","voix":38},{"nuance":"SOC","nom":"Mme Marie LE VERN","voix":17},{"nuance":"COM","nom":"M. Sébastien JUMEL","voix":15},{"nuance":"DIV","nom":"M. David GROUT","voix":3},{"nuance":"EXG","nom":"M. Éric MOISAN","voix":1},{"nuance":"DVG","nom":"M. Michel CORDIN","voix":0}]}