{"nom":"Le Petit-Quevilly","circ":"3ème circonscription","dpt":"Seine-Maritime","inscrits":12708,"abs":7114,"votants":5594,"blancs":128,"nuls":34,"exp":5432,"res":[{"nuance":"REM","nom":"M. Cyrille GRENOT","voix":1466},{"nuance":"FN","nom":"M. Guillaume PENNELLE","voix":1083},{"nuance":"SOC","nom":"Mme Luce PANE","voix":1076},{"nuance":"COM","nom":"M. Hubert WULFRANC","voix":852},{"nuance":"DVG","nom":"M. Abdelkrim MARCHANI","voix":291},{"nuance":"LR","nom":"M. Jonas HADDAD","voix":222},{"nuance":"EXG","nom":"M. Pascal LE MANACH","voix":115},{"nuance":"ECO","nom":"Mme Jemâa SAAD","voix":113},{"nuance":"DLF","nom":"Mme Nadine JAZÉ","voix":93},{"nuance":"DIV","nom":"Mme Evelyne DELBOS","voix":50},{"nuance":"DIV","nom":"M. Laurent MONTARON","voix":43},{"nuance":"EXG","nom":"M. Rémi CANDELIER","voix":28},{"nuance":"DVG","nom":"M. Nicolas HUET DE BARROS","voix":0}]}