{"nom":"Aulnay","circ":"3ème circonscription","dpt":"Charente-Maritime","inscrits":1056,"abs":556,"votants":500,"blancs":9,"nuls":7,"exp":484,"res":[{"nuance":"REM","nom":"M. Jean-Philippe ARDOUIN","voix":150},{"nuance":"LR","nom":"M. Frederic NEVEU","voix":76},{"nuance":"FN","nom":"Mme Rachel COINTET","voix":74},{"nuance":"SOC","nom":"Mme Francoise MESNARD","voix":68},{"nuance":"DVG","nom":"M. Julien PAPINEAU","voix":41},{"nuance":"FI","nom":"M. Remy CATROU","voix":30},{"nuance":"UDI","nom":"Mme Henriette DIADIO-DASYLVA","voix":12},{"nuance":"DVD","nom":"M. Patrick CHEBROUX","voix":9},{"nuance":"DIV","nom":"M. Alain GEORGEON","voix":9},{"nuance":"ECO","nom":"Mme Joelle DE CORTE","voix":3},{"nuance":"DVG","nom":"M. Frederic SANANES","voix":3},{"nuance":"RDG","nom":"Mme Renée Eliane BENCHIMOL LAURIBE","voix":2},{"nuance":"EXD","nom":"M. Eric BELLEPERCHE","voix":2},{"nuance":"DVD","nom":"M. Alexandre BEAUVAIS","voix":2},{"nuance":"COM","nom":"Mme Marie-France MOQUET","voix":1},{"nuance":"DVG","nom":"M. Bernard CHRETIEN","voix":1},{"nuance":"EXG","nom":"M. Jean-Louis LAVAZEC","voix":1},{"nuance":"DIV","nom":"Mme Isabelle NINVIRTH","voix":0}]}