{"nom":"Quézac","circ":"1ère circonscription","dpt":"Cantal","inscrits":255,"abs":111,"votants":144,"blancs":3,"nuls":1,"exp":140,"res":[{"nuance":"REM","nom":"M. François DANEMANS","voix":40},{"nuance":"LR","nom":"M. Vincent DESCOEUR","voix":40},{"nuance":"DVD","nom":"M. François VERMANDE","voix":25},{"nuance":"FI","nom":"M. Thierry BONHOURE","voix":24},{"nuance":"FN","nom":"Mme Marie-Claire NATHER","voix":7},{"nuance":"ECO","nom":"M. Stéphane FRÉCHOU","voix":2},{"nuance":"COM","nom":"M. Jean-François BARRIER","voix":1},{"nuance":"ECO","nom":"M. Michel FABRE","voix":1},{"nuance":"EXG","nom":"M. Rémy DAUVILLIER","voix":0},{"nuance":"DIV","nom":"M. Grégory PAUTRAT","voix":0}]}