{"nom":"Asnelles","circ":"5ème circonscription","dpt":"Calvados","inscrits":555,"abs":250,"votants":305,"blancs":4,"nuls":0,"exp":301,"res":[{"nuance":"LR","nom":"M. Cédric NOUVELOT","voix":86},{"nuance":"REM","nom":"M. Bertrand BOUYX","voix":74},{"nuance":"FN","nom":"Mme Christine BISSON","voix":65},{"nuance":"DVG","nom":"Mme Isabelle ATTARD","voix":56},{"nuance":"EXG","nom":"Mme Isabelle PELTRE","voix":8},{"nuance":"ECO","nom":"M. Christophe SADY","voix":5},{"nuance":"DLF","nom":"M. Eric BEAUDOIN","voix":5},{"nuance":"DIV","nom":"M. Simon GERVAIS","voix":2},{"nuance":"DVG","nom":"M. Yves ROUILLÉ","voix":0}]}