{"nom":"Saint-Ouen-le-Pin","circ":"3ème circonscription","dpt":"Calvados","inscrits":222,"abs":108,"votants":114,"blancs":2,"nuls":0,"exp":112,"res":[{"nuance":"MDM","nom":"Mme Florence LEHERICY","voix":34},{"nuance":"SOC","nom":"Mme Clotilde VALTER","voix":23},{"nuance":"LR","nom":"M. Sébastien LECLERC","voix":19},{"nuance":"FN","nom":"Mme Christelle LECHEVALIER-LETARD","voix":16},{"nuance":"FI","nom":"M. Didier CANU","voix":15},{"nuance":"ECO","nom":"M. Jacques BESSIN","voix":4},{"nuance":"COM","nom":"M. Serge LOISEAU","voix":1},{"nuance":"DVG","nom":"M. Wilfried VAN OOST","voix":0},{"nuance":"DIV","nom":"Mme Karine SEGUIN","voix":0},{"nuance":"DVG","nom":"M. Henri NOURRY","voix":0},{"nuance":"EXG","nom":"M. Michel LANGEVIN","voix":0},{"nuance":"DLF","nom":"M. Steven MAFIODO","voix":0},{"nuance":"DVG","nom":"M. Angelo LECOQ","voix":0}]}