{"nom":"Vaux-sur-Aure","circ":"5ème circonscription","dpt":"Calvados","inscrits":268,"abs":103,"votants":165,"blancs":3,"nuls":1,"exp":161,"res":[{"nuance":"REM","nom":"M. Bertrand BOUYX","voix":83},{"nuance":"DVG","nom":"Mme Isabelle ATTARD","voix":33},{"nuance":"LR","nom":"M. Cédric NOUVELOT","voix":22},{"nuance":"FN","nom":"Mme Christine BISSON","voix":13},{"nuance":"ECO","nom":"M. Christophe SADY","voix":5},{"nuance":"EXG","nom":"Mme Isabelle PELTRE","voix":4},{"nuance":"DLF","nom":"M. Eric BEAUDOIN","voix":1},{"nuance":"DVG","nom":"M. Yves ROUILLÉ","voix":0},{"nuance":"DIV","nom":"M. Simon GERVAIS","voix":0}]}