{"nom":"Saint-Pierre-du-Mont","circ":"5ème circonscription","dpt":"Calvados","inscrits":69,"abs":22,"votants":47,"blancs":0,"nuls":0,"exp":47,"res":[{"nuance":"REM","nom":"M. Bertrand BOUYX","voix":14},{"nuance":"LR","nom":"M. Cédric NOUVELOT","voix":13},{"nuance":"FN","nom":"Mme Christine BISSON","voix":12},{"nuance":"DVG","nom":"Mme Isabelle ATTARD","voix":7},{"nuance":"DLF","nom":"M. Eric BEAUDOIN","voix":1},{"nuance":"EXG","nom":"Mme Isabelle PELTRE","voix":0},{"nuance":"DVG","nom":"M. Yves ROUILLÉ","voix":0},{"nuance":"ECO","nom":"M. Christophe SADY","voix":0},{"nuance":"DIV","nom":"M. Simon GERVAIS","voix":0}]}