{"nom":"Porte du Ried","circ":"1ère circonscription","dpt":"Haut-Rhin","inscrits":1505,"abs":611,"votants":894,"blancs":8,"nuls":5,"exp":881,"res":[{"nuance":"LR","nom":"M. Eric STRAUMANN","voix":428},{"nuance":"REM","nom":"Mme Stéphanie VILLEMIN","voix":209},{"nuance":"FN","nom":"Mme Marie-Hélène DE LACOSTE LAREYMONDIE","voix":86},{"nuance":"ECO","nom":"M. Frédéric HILBERT","voix":40},{"nuance":"DIV","nom":"M. Christophe KLEITZ","voix":25},{"nuance":"DVD","nom":"M. Philippe ROGALA","voix":22},{"nuance":"REG","nom":"Mme Nadia HOOG","voix":22},{"nuance":"FI","nom":"M. Didier OTTERMANN","voix":17},{"nuance":"DLF","nom":"Mme Sabrina BLONDÉ","voix":11},{"nuance":"DIV","nom":"M. Fabien BADARIOTTI","voix":6},{"nuance":"EXG","nom":"M. Gilles SCHAFFAR","voix":5},{"nuance":"DIV","nom":"Mme Lydia BEROFF","voix":3},{"nuance":"DIV","nom":"M. Erol YUCEL","voix":2},{"nuance":"COM","nom":"Mme Régine MARIAGE","voix":2},{"nuance":"DIV","nom":"M. Joël JEROME","voix":2},{"nuance":"RDG","nom":"Mme Marie-Agnès STRAZEL","voix":1},{"nuance":"DIV","nom":"M. Christophe ELCHINGER","voix":0},{"nuance":"DVG","nom":"M. Paul MARTIN","voix":0}]}