{"nom":"Kingersheim","circ":"6ème circonscription","dpt":"Haut-Rhin","inscrits":9013,"abs":5073,"votants":3940,"blancs":43,"nuls":16,"exp":3881,"res":[{"nuance":"REM","nom":"M. Bruno FUCHS","voix":1337},{"nuance":"FN","nom":"M. Sylvain MARCELLI","voix":770},{"nuance":"UDI","nom":"M. Francis HILLMEYER","voix":552},{"nuance":"FI","nom":"M. Philippe DUFFAU","voix":395},{"nuance":"DVD","nom":"Mme Lara MILLION","voix":208},{"nuance":"REG","nom":"M. Laurent ROTH","voix":208},{"nuance":"SOC","nom":"M. Pierre PARRA","voix":107},{"nuance":"ECO","nom":"M. Ralph WICKY","voix":77},{"nuance":"DLF","nom":"Mme Caroline WIDLOECHER-REYMANN","voix":59},{"nuance":"ECO","nom":"Mme Martine LAPOUBLE-BARTHOU","voix":57},{"nuance":"EXG","nom":"Mme Nathalie MULOT","voix":22},{"nuance":"EXD","nom":"Mme Mildred FREY","voix":22},{"nuance":"DIV","nom":"M. David BIZET","voix":20},{"nuance":"DIV","nom":"M. Mehmet Han SIMSEK","voix":19},{"nuance":"DIV","nom":"Mme Fausta DE MAESTRI","voix":16},{"nuance":"COM","nom":"M. Christophe POUYSEGUR","voix":12}]}