{"nom":"Dangeau","circ":"4ème circonscription","dpt":"Eure-et-Loir","inscrits":686,"abs":316,"votants":370,"blancs":5,"nuls":2,"exp":363,"res":[{"nuance":"UDI","nom":"M. Philippe VIGIER","voix":164},{"nuance":"FN","nom":"M. Vincent COLLO","voix":91},{"nuance":"REM","nom":"Mme Clémence ROUVIER","voix":57},{"nuance":"DVG","nom":"M. Fabien VERDIER","voix":17},{"nuance":"FI","nom":"Mme Sophie SINATTI","voix":14},{"nuance":"ECO","nom":"Mme Nachida BARRE","voix":5},{"nuance":"EXG","nom":"Mme Anne-Laure ASSAYAG","voix":4},{"nuance":"COM","nom":"Mme Dominique GARCIA","voix":4},{"nuance":"DVD","nom":"M. Damien VILLETTE","voix":4},{"nuance":"DIV","nom":"M. Florian TESSIER","voix":2},{"nuance":"DLF","nom":"Mme Florence BERNARD","voix":1}]}