{"nom":"Meilhan-sur-Garonne","circ":"2ème circonscription","dpt":"Lot-et-Garonne","inscrits":910,"abs":296,"votants":614,"blancs":10,"nuls":11,"exp":593,"res":[{"nuance":"SOC","nom":"M. Matthias FEKL","voix":182},{"nuance":"REM","nom":"M. Alexandre FRESCHI","voix":147},{"nuance":"FN","nom":"Mme Hélène LAPORTE","voix":100},{"nuance":"FI","nom":"M. Sylvio GUINGAN","voix":45},{"nuance":"LR","nom":"M. Emilien ROSO","voix":35},{"nuance":"DVD","nom":"M. Jean-François BETHUS","voix":35},{"nuance":"COM","nom":"M. Michel CERUTI","voix":31},{"nuance":"ECO","nom":"Mme Mathilde BOEUF","voix":7},{"nuance":"DLF","nom":"Mme Dalila BENCHELIFF","voix":4},{"nuance":"DIV","nom":"Mme Muriel DUHIL","voix":3},{"nuance":"DVD","nom":"M. Patrick MAURIN","voix":2},{"nuance":"ECO","nom":"M. David LACUBE","voix":1},{"nuance":"EXG","nom":"Mme Zina AHMIMOU","voix":1}]}