{"nom":"Lagrâce-Dieu","circ":"7ème circonscription","dpt":"Haute-Garonne","inscrits":353,"abs":148,"votants":205,"blancs":7,"nuls":2,"exp":196,"res":[{"nuance":"REM","nom":"Mme Elisabeth TOUTUT-PICARD","voix":68},{"nuance":"FN","nom":"Mme Marie DOMBES","voix":33},{"nuance":"FI","nom":"M. Christophe BEX","voix":23},{"nuance":"SOC","nom":"Mme Marie-Caroline TEMPESTA","voix":22},{"nuance":"LR","nom":"Mme Françoise BORRET","voix":15},{"nuance":"ECO","nom":"Mme Catherine RENAUX","voix":11},{"nuance":"COM","nom":"Mme Danielle TENSA","voix":10},{"nuance":"DLF","nom":"M. Damien JEANNE","voix":5},{"nuance":"DIV","nom":"M. Roger STROBEL","voix":4},{"nuance":"DIV","nom":"Mme Myriam CRÉDOT","voix":3},{"nuance":"DVD","nom":"Mme Marie-Gabrielle DE LA DORIE","voix":1},{"nuance":"EXG","nom":"Mme Malena ADRADA","voix":1},{"nuance":"ECO","nom":"M. Pierre MOURE","voix":0}]}