{"nom":"Saint-Barthélemy-le-Plain","circ":"2ème circonscription","dpt":"Ardèche","inscrits":633,"abs":324,"votants":309,"blancs":6,"nuls":2,"exp":301,"res":[{"nuance":"REM","nom":"Mme Laurette GOUYET-POMMARET","voix":74},{"nuance":"FN","nom":"Mme Odile LASFARGUES-BOUYON","voix":56},{"nuance":"DVD","nom":"M. Jean-Paul VALLON","voix":55},{"nuance":"LR","nom":"M. Marc-Antoine QUENETTE","voix":35},{"nuance":"SOC","nom":"M. Olivier DUSSOPT","voix":33},{"nuance":"FI","nom":"Mme Samia HASNAOUI","voix":23},{"nuance":"DLF","nom":"Mme Isabelle FRANÇOIS","voix":11},{"nuance":"ECO","nom":"Mme Nadia SENNI","voix":9},{"nuance":"COM","nom":"M. Daniel BABAROSSA","voix":5},{"nuance":"DIV","nom":"Mme Isabelle STRUBI","voix":0},{"nuance":"EXG","nom":"M. Christophe MARCHISIO","voix":0},{"nuance":"EXD","nom":"M. Jean-Paul Louis VALLON","voix":0}]}