{"nom":"Castifao","circ":"2ème circonscription","dpt":"Haute-Corse","inscrits":212,"abs":84,"votants":128,"blancs":0,"nuls":0,"exp":128,"res":[{"nuance":"REG","nom":"M. Jean-Félix ACQUAVIVA","voix":75},{"nuance":"REM","nom":"M. Francis GIUDICI","voix":23},{"nuance":"FI","nom":"M. Jean MOGHRAOUI","voix":9},{"nuance":"DVD","nom":"M. Jean-Martin MONDOLONI","voix":7},{"nuance":"LR","nom":"Mme Stéphanie GRIMALDI","voix":7},{"nuance":"FN","nom":"Mme Dadou JACOB DIT LUZIE-ALBERTINI","voix":2},{"nuance":"DVG","nom":"M. Henri MALOSSE","voix":2},{"nuance":"COM","nom":"Mme Marie Jeanne FEDI","voix":2},{"nuance":"DIV","nom":"M. Le BARON MARIANI","voix":1},{"nuance":"DIV","nom":"M. Lionel SONNETTE","voix":0},{"nuance":"EXG","nom":"M. Didier GIBAUD","voix":0}]}