{"nom":"La Chapelle-Saint-Rémy","circ":"5ème circonscription","dpt":"Sarthe","inscrits":691,"abs":358,"votants":333,"blancs":8,"nuls":4,"exp":321,"res":[{"nuance":"LR","nom":"M. Jean-Carles GRELIER","voix":89},{"nuance":"REM","nom":"M. Willy COLIN","voix":70},{"nuance":"FN","nom":"M. Eric DE VILMAREST","voix":62},{"nuance":"FI","nom":"M. Luc-Marie FABUREL","voix":41},{"nuance":"ECO","nom":"Mme Sophie BRINGUY","voix":14},{"nuance":"SOC","nom":"M. Samuel CADEAU","voix":8},{"nuance":"EXD","nom":"Mme Aurélie ARSENIO","voix":7},{"nuance":"DIV","nom":"M. Arnaud ROLLAND","voix":7},{"nuance":"COM","nom":"M. Vincent PETIT","voix":7},{"nuance":"EXG","nom":"Mme Karine FOUQUET","voix":6},{"nuance":"DLF","nom":"Mme Cécile BAYLE DE JESSÉ","voix":5},{"nuance":"EXD","nom":"Mme Brigitte DUPIN","voix":3},{"nuance":"DIV","nom":"M. Antoine HERVIEU","voix":2}]}