{"nom":"Chérisay","circ":"1ère circonscription","dpt":"Sarthe","inscrits":246,"abs":107,"votants":139,"blancs":3,"nuls":0,"exp":136,"res":[{"nuance":"REM","nom":"M. Damien PICHEREAU","voix":41},{"nuance":"LR","nom":"Mme Christelle MORANÇAIS","voix":29},{"nuance":"SOC","nom":"Mme Françoise DUBOIS","voix":23},{"nuance":"FN","nom":"Mme Marie GENEVREY","voix":22},{"nuance":"FI","nom":"M. Loïc MORISOT","voix":9},{"nuance":"DLF","nom":"M. Philippe CORDIER","voix":6},{"nuance":"ECO","nom":"Mme Isabelle SEVERE","voix":4},{"nuance":"DIV","nom":"M. Jean-François GAZENGEL","voix":1},{"nuance":"EXD","nom":"Mme Fabienne DE LA CHAPELLE","voix":1},{"nuance":"DVD","nom":"M. John Jacques MARSHALL","voix":0},{"nuance":"DIV","nom":"Mme Ghislaine CHARRONNEAU","voix":0},{"nuance":"DVG","nom":"Mme Catherine GOUHIER","voix":0},{"nuance":"EXD","nom":"M. Louis NOGUÈS","voix":0},{"nuance":"EXG","nom":"Mme Sylvie MAILLET","voix":0}]}