{"nom":"Morcenx","circ":"3ème circonscription","dpt":"Landes","inscrits":3422,"abs":1410,"votants":2012,"blancs":58,"nuls":33,"exp":1921,"res":[{"nuance":"SOC","nom":"M. Boris VALLAUD","voix":594},{"nuance":"REM","nom":"M. Jean-Pierre STEINER","voix":411},{"nuance":"FI","nom":"M. Philippe DUBOURG","voix":330},{"nuance":"FN","nom":"Mme Océane RAVIX","voix":212},{"nuance":"COM","nom":"Mme Michèle BERTHOU","voix":119},{"nuance":"UDI","nom":"Mme Marie Claire DUPRAT","voix":76},{"nuance":"ECO","nom":"M. Richard BIDEGARAY","voix":45},{"nuance":"DVD","nom":"M. Yann BRONGNIART","voix":35},{"nuance":"DLF","nom":"Mme Nicole DE LETTER","voix":31},{"nuance":"DIV","nom":"Mme Marie RADOSZ","voix":21},{"nuance":"DVD","nom":"Mme Christelle LASSORT","voix":17},{"nuance":"ECO","nom":"Mme Laetitia HIRSCH","voix":17},{"nuance":"EXG","nom":"M. Nicolas VION","voix":13}]}