{"nom":"Saint-Sulpice-et-Cameyrac","circ":"4ème circonscription","dpt":"Gironde","inscrits":3527,"abs":1798,"votants":1729,"blancs":21,"nuls":9,"exp":1699,"res":[{"nuance":"REM","nom":"M. Aziz S'KALLI-BOUAZIZA","voix":591},{"nuance":"UDI","nom":"M. Hubert LAPORTE","voix":363},{"nuance":"FN","nom":"M. Serge HADON","voix":207},{"nuance":"FI","nom":"Mme Maud BESSON","voix":185},{"nuance":"SOC","nom":"M. Alain DAVID","voix":180},{"nuance":"ECO","nom":"Mme Laure DESVALOIS","voix":55},{"nuance":"DLF","nom":"Mme Martine HOSTIER","voix":37},{"nuance":"COM","nom":"Mme Berivan BAL","voix":24},{"nuance":"DIV","nom":"Mme Daphné DAUMAND","voix":21},{"nuance":"EXG","nom":"Mme Anne-Isabelle BRIVARY","voix":13},{"nuance":"EXG","nom":"Mme Christine HÉRAUD","voix":12},{"nuance":"DIV","nom":"M. Jean-Louis GILLES","voix":11}]}