{"nom":"Vensac","circ":"5ème circonscription","dpt":"Gironde","inscrits":810,"abs":366,"votants":444,"blancs":5,"nuls":0,"exp":439,"res":[{"nuance":"REM","nom":"M. Benoit SIMIAN","voix":138},{"nuance":"FN","nom":"M. Grégoire DE FOURNAS","voix":107},{"nuance":"SOC","nom":"Mme Pascale GOT","voix":69},{"nuance":"LR","nom":"Mme Florence LEGRAND","voix":48},{"nuance":"FI","nom":"Mme Martine CALVO","voix":38},{"nuance":"ECO","nom":"M. Stéphane SAUBUSSE","voix":9},{"nuance":"DLF","nom":"Mme Sonia COLEMYN","voix":9},{"nuance":"COM","nom":"M. Stéphane LE BOT","voix":8},{"nuance":"DVD","nom":"M. Christophe CAPELLI","voix":6},{"nuance":"EXD","nom":"M. François-Régis TAVEAU","voix":4},{"nuance":"DIV","nom":"Mme Thi Be NGUYEN","voix":3},{"nuance":"DIV","nom":"M. Julien BRARD","voix":0},{"nuance":"EXG","nom":"M. Rémy COSTE","voix":0}]}