{"nom":"La Valla-sur-Rochefort","circ":"6ème circonscription","dpt":"Loire","inscrits":92,"abs":31,"votants":61,"blancs":5,"nuls":1,"exp":55,"res":[{"nuance":"LR","nom":"M. Paul SALEN","voix":24},{"nuance":"REM","nom":"M. Julien BOROWCZYK","voix":13},{"nuance":"FN","nom":"Mme Sophie ROBERT","voix":11},{"nuance":"ECO","nom":"M. Jean DUVERGER","voix":3},{"nuance":"DLF","nom":"Mme Marie GONCALVES","voix":3},{"nuance":"FI","nom":"Mme Sadia Nadia SEGHIR","voix":1},{"nuance":"ECO","nom":"M. Bernard CHUZEVILLE","voix":0},{"nuance":"DIV","nom":"M. Ludovic VAGINAY","voix":0},{"nuance":"DVD","nom":"M. Nicolas POIRIEUX","voix":0},{"nuance":"EXG","nom":"Mme Cécile MAISONNETTE","voix":0},{"nuance":"DIV","nom":"M. Michel CUENIN","voix":0}]}