{"nom":"Marlhes","circ":"4ème circonscription","dpt":"Loire","inscrits":968,"abs":384,"votants":584,"blancs":5,"nuls":2,"exp":577,"res":[{"nuance":"LR","nom":"M. Dino CINIERI","voix":238},{"nuance":"REM","nom":"M. David KAUFFER","voix":168},{"nuance":"FN","nom":"Mme Raphaëlle JEANSON","voix":65},{"nuance":"COM","nom":"M. Christophe FAVERJON","voix":39},{"nuance":"FI","nom":"M. Léo CHAVAS","voix":34},{"nuance":"DLF","nom":"M. Patrick MIGNON","voix":12},{"nuance":"DVD","nom":"M. Olivier JOLY","voix":10},{"nuance":"ECO","nom":"M. Gérard GUILLAUMIN","voix":7},{"nuance":"EXG","nom":"Mme Françoise LECLET","voix":3},{"nuance":"DIV","nom":"M. Jean-Christophe DEBENS","voix":1},{"nuance":"ECO","nom":"M. Pascal THOMAS","voix":0},{"nuance":"EXD","nom":"M. François SHEMATSI","voix":0}]}