{"nom":"Linselles","circ":"10ème circonscription","dpt":"Nord","inscrits":6557,"abs":3348,"votants":3209,"blancs":50,"nuls":7,"exp":3152,"res":[{"nuance":"REM","nom":"Mme Sophie TAÏEB","voix":998},{"nuance":"LR","nom":"M. Vincent LEDOUX","voix":973},{"nuance":"FN","nom":"Mme Virginie ROSEZ","voix":499},{"nuance":"FI","nom":"Mme Adélie CORMONT","voix":290},{"nuance":"ECO","nom":"M. Olivier DESCAMPS","voix":119},{"nuance":"SOC","nom":"Mme Yasmina CHIGRI","voix":112},{"nuance":"DLF","nom":"M. Frédéric DEBRUYNE","voix":49},{"nuance":"EXD","nom":"M. Christian BAECKEROOT","voix":28},{"nuance":"DIV","nom":"M. Olivier DURNEZ","voix":19},{"nuance":"COM","nom":"Mme Jocelyne LEFEBVRE","voix":17},{"nuance":"ECO","nom":"M. Oueb LEUCHI","voix":16},{"nuance":"EXG","nom":"M. Christophe CHARLON","voix":16},{"nuance":"DVD","nom":"M. Bernard DUJARDIN","voix":10},{"nuance":"DIV","nom":"Mme Léa DETURCHE","voix":6}]}