{"nom":"Socx","circ":"14ème circonscription","dpt":"Nord","inscrits":800,"abs":325,"votants":475,"blancs":2,"nuls":7,"exp":466,"res":[{"nuance":"LR","nom":"M. Paul CHRISTOPHE","voix":167},{"nuance":"REM","nom":"M. Julien LEMAITTE","voix":156},{"nuance":"FN","nom":"M. Yohann DUVAL","voix":55},{"nuance":"FI","nom":"Mme Delphine DECOSTER","voix":39},{"nuance":"RDG","nom":"M. Sylvie BRACHET","voix":22},{"nuance":"ECO","nom":"Mme Myriam SANTHUNE","voix":11},{"nuance":"SOC","nom":"M. Christian DEVOS","voix":5},{"nuance":"COM","nom":"Mme Nathalie BENALLA","voix":5},{"nuance":"EXD","nom":"M. Jean-Paul TISSERAND","voix":4},{"nuance":"DIV","nom":"M. Stéphane DUMONT","voix":1},{"nuance":"EXG","nom":"M. David HAILLANT","voix":1}]}