{"nom":"Saint-Jean-de-la-Léqueraye","circ":"3ème circonscription","dpt":"Eure","inscrits":51,"abs":20,"votants":31,"blancs":0,"nuls":0,"exp":31,"res":[{"nuance":"MDM","nom":"Mme Marie TAMARELLE-VERHAEGHE","voix":11},{"nuance":"FN","nom":"M. Timothée HOUSSIN","voix":7},{"nuance":"UDI","nom":"M. Pierre BIBET","voix":5},{"nuance":"DVD","nom":"Mme Isabelle DUONG","voix":2},{"nuance":"ECO","nom":"Mme Christine RÉGENTÊTE","voix":2},{"nuance":"FI","nom":"M. Gwenhaël LAVERGNE","voix":2},{"nuance":"SOC","nom":"Mme Marie-Claire HAKI","voix":2},{"nuance":"DIV","nom":"Mme Béatrice PALACIOS","voix":0},{"nuance":"ECO","nom":"M. Mathieu NORMAND","voix":0},{"nuance":"DVG","nom":"Mme Christine AMANIEU","voix":0},{"nuance":"EXG","nom":"Mme Claudette BALLEYDIER","voix":0}]}