{"nom":"Marbois","circ":"1ère circonscription","dpt":"Eure","inscrits":990,"abs":484,"votants":506,"blancs":9,"nuls":2,"exp":495,"res":[{"nuance":"REM","nom":"M. Bruno LE MAIRE","voix":213},{"nuance":"FN","nom":"Mme Fabienne DELACOUR","voix":172},{"nuance":"FI","nom":"M. Michaël DESPRÉS","voix":45},{"nuance":"LR","nom":"Mme Coumba DIOUKHANÉ","voix":23},{"nuance":"ECO","nom":"Mme Laetitia SANCHEZ","voix":17},{"nuance":"ECO","nom":"Mme Véronique ALLO","voix":9},{"nuance":"EXG","nom":"M. Denis PANIER","voix":4},{"nuance":"DIV","nom":"M. Nicolas MIGUET","voix":4},{"nuance":"DIV","nom":"Mme Frédérique MANLEY","voix":3},{"nuance":"DIV","nom":"Mme Michaële LE GOFF","voix":3},{"nuance":"DLF","nom":"Mme Fataumata NIAKATE","voix":2},{"nuance":"COM","nom":"Mme Maryata KONTÉ","voix":0},{"nuance":"DIV","nom":"M. Remzi SEKERCI","voix":0},{"nuance":"DIV","nom":"Mme Minatou GRAIBIS","voix":0},{"nuance":"DIV","nom":"M. Sid-Ali FERROUK","voix":0},{"nuance":"DVG","nom":"Mme Patricia SAINT-GEORGES","voix":0},{"nuance":"DIV","nom":"M. Wilfried PARIS","voix":0}]}