{"nom":"Saint-Jeures","circ":"1ère circonscription","dpt":"Haute-Loire","inscrits":838,"abs":328,"votants":510,"blancs":7,"nuls":1,"exp":502,"res":[{"nuance":"LR","nom":"Mme Isabelle VALENTIN","voix":208},{"nuance":"REM","nom":"Mme Cécile GALLIEN","voix":162},{"nuance":"FN","nom":"M. Fabien ALBERTINI","voix":50},{"nuance":"FI","nom":"Mme Martine DEJEAN","voix":39},{"nuance":"ECO","nom":"Mme Anne BADIAN-LHERMET","voix":13},{"nuance":"SOC","nom":"M. Fabrice FARISON","voix":12},{"nuance":"DVG","nom":"M. Yves PRAT","voix":9},{"nuance":"DLF","nom":"M. Gabriel CARDAIRE","voix":4},{"nuance":"ECO","nom":"M. Philippe COCHET","voix":2},{"nuance":"DIV","nom":"M. Michaël MASCLET","voix":2},{"nuance":"EXG","nom":"M. Pierre MICHALLET","voix":1},{"nuance":"DIV","nom":"Mme Hélène DENIS","voix":0}]}