{"nom":"Le Breuil","circ":"3ème circonscription","dpt":"Saône-et-Loire","inscrits":3012,"abs":1457,"votants":1555,"blancs":35,"nuls":15,"exp":1505,"res":[{"nuance":"SOC","nom":"M. Philippe BAUMEL","voix":500},{"nuance":"REM","nom":"M. Rémy REBEYROTTE","voix":371},{"nuance":"LR","nom":"M. Charles LANDRE","voix":277},{"nuance":"FN","nom":"M. Quentin BIJARD","voix":161},{"nuance":"FI","nom":"M. Pierre ACEITUNO","voix":102},{"nuance":"ECO","nom":"M. Pierre-Etienne GRAFFARD","voix":27},{"nuance":"COM","nom":"M. Serge DESBROSSES","voix":23},{"nuance":"DLF","nom":"Mme France ROBERT","voix":14},{"nuance":"DVD","nom":"Mme Murielle BERTHELIER","voix":13},{"nuance":"DIV","nom":"Mme Florence PANDROT","voix":9},{"nuance":"EXG","nom":"Mme Julie LUCOTTE","voix":5},{"nuance":"DVD","nom":"M. Sylvain GARCIA","voix":2},{"nuance":"ECO","nom":"M. Roland ESSAYAN","voix":1}]}