{"nom":"Ervy-le-Châtel","circ":"2ème circonscription","dpt":"Aube","inscrits":757,"abs":371,"votants":386,"blancs":2,"nuls":3,"exp":381,"res":[{"nuance":"DVD","nom":"Mme Sybille BERTAIL","voix":116},{"nuance":"FN","nom":"M. Jean-Christophe LEFEVRE","voix":83},{"nuance":"REM","nom":"Mme Djamila HADDAD","voix":69},{"nuance":"LR","nom":"Mme Valérie BAZIN-MALGRAS","voix":48},{"nuance":"FI","nom":"Mme Elise GEHIN","voix":31},{"nuance":"SOC","nom":"M. Virgil HENNEQUIN","voix":17},{"nuance":"DIV","nom":"Mme Françoise JOUVE","voix":5},{"nuance":"DIV","nom":"M. Frédéric FAYS","voix":5},{"nuance":"DVG","nom":"Mme Patricia PEYRAUD","voix":3},{"nuance":"DIV","nom":"M. Olivier TAMARIO","voix":1},{"nuance":"COM","nom":"Mme Gisèle MALAVAL","voix":1},{"nuance":"ECO","nom":"M. Benjamin BIRENE","voix":1},{"nuance":"EXG","nom":"M. Julien CYNOBER","voix":1}]}