{"nom":"Libermont","circ":"6ème circonscription","dpt":"Oise","inscrits":183,"abs":106,"votants":77,"blancs":1,"nuls":1,"exp":75,"res":[{"nuance":"REM","nom":"Mme Carole BUREAU-BONNARD","voix":28},{"nuance":"FN","nom":"M. Michel GUINIOT","voix":18},{"nuance":"COM","nom":"M. Patrice CARVALHO","voix":11},{"nuance":"LR","nom":"M. Eric DE VALROGER","voix":10},{"nuance":"FI","nom":"Mme Géraldine MINET","voix":6},{"nuance":"ECO","nom":"Mme Caroline MARZUCCHETTI","voix":1},{"nuance":"DLF","nom":"Mme Véronique ROGEZ","voix":1},{"nuance":"EXG","nom":"M. Jean-Marc ISKIN","voix":0},{"nuance":"DIV","nom":"M. Garry CAMBON","voix":0},{"nuance":"DIV","nom":"Mme Marie VERYEPE","voix":0}]}