{"nom":"Draché","circ":"3ème circonscription","dpt":"Indre-et-Loire","inscrits":563,"abs":281,"votants":282,"blancs":12,"nuls":0,"exp":270,"res":[{"nuance":"UDI","nom":"Mme Sophie AUCONIE","voix":83},{"nuance":"SOC","nom":"Mme Marisol TOURAINE","voix":81},{"nuance":"FI","nom":"Mme Sylvie ADOLPHE","voix":30},{"nuance":"FN","nom":"Mme Eva KUKULSKI","voix":24},{"nuance":"DVD","nom":"M. Marc ANGENAULT","voix":17},{"nuance":"ECO","nom":"Mme Marie-Agnès PELTIER","voix":14},{"nuance":"DLF","nom":"M. François-Xavier DECROP","voix":9},{"nuance":"EXG","nom":"Mme Claire DELORE","voix":5},{"nuance":"COM","nom":"M. Ronan LEBERT","voix":2},{"nuance":"EXG","nom":"M. Thomas JOUHANNAUD","voix":2},{"nuance":"ECO","nom":"Mme Marie-Pierre HAGE","voix":2},{"nuance":"DIV","nom":"M. Philippe RUBEL","voix":1},{"nuance":"DVD","nom":"M. Robert DE PREVOISIN","voix":0}]}