{"nom":"Roussieux","circ":"3ème circonscription","dpt":"Drôme","inscrits":28,"abs":16,"votants":12,"blancs":0,"nuls":0,"exp":12,"res":[{"nuance":"SOC","nom":"Mme Pascale ROCHAS","voix":5},{"nuance":"FI","nom":"M. Didier THEVENIEAU","voix":4},{"nuance":"FN","nom":"Mme Rachel REYGNIER","voix":1},{"nuance":"ECO","nom":"Mme Martine MORVAN","voix":1},{"nuance":"REM","nom":"Mme Célia DE LAVERGNE","voix":1},{"nuance":"ECO","nom":"M. Frédéric AMANDOLA","voix":0},{"nuance":"ECO","nom":"M. Gabriel LACROIX","voix":0},{"nuance":"COM","nom":"Mme Chantal BÉLÉZY","voix":0},{"nuance":"DIV","nom":"Mme Adeline KARGUÉ","voix":0},{"nuance":"EXG","nom":"M. Charly CHAMPMARTIN","voix":0},{"nuance":"LR","nom":"M. Paul BERARD","voix":0},{"nuance":"DVD","nom":"M. Rodolphe DEJOUR","voix":0},{"nuance":"DLF","nom":"M. Norbert AGUERA","voix":0},{"nuance":"DIV","nom":"Mme Brigitte ROUSSELET","voix":0}]}