{"nom":"La Ferrière","circ":"1ère circonscription","dpt":"Vendée","inscrits":3938,"abs":1782,"votants":2156,"blancs":31,"nuls":15,"exp":2110,"res":[{"nuance":"MDM","nom":"M. Philippe LATOMBE","voix":896},{"nuance":"LR","nom":"M. Alain LEBOEUF","voix":474},{"nuance":"FI","nom":"Mme Gwenaëlle GRIETENS","voix":223},{"nuance":"SOC","nom":"Mme Cécile DREURE","voix":174},{"nuance":"FN","nom":"Mme Catherine ROY","voix":139},{"nuance":"ECO","nom":"M. Guy BATIOT","voix":87},{"nuance":"DIV","nom":"M. Théo RIVIERE","voix":27},{"nuance":"DLF","nom":"Mme Marie-Thérèse CHÂTILLON","voix":24},{"nuance":"EXG","nom":"M. Gilles ROBIN","voix":22},{"nuance":"DVD","nom":"Mme Marie-Hélène LAMIOT","voix":18},{"nuance":"COM","nom":"M. Pierrick CHAIGNE","voix":16},{"nuance":"DIV","nom":"Mme Frédérique BISIERE","voix":7},{"nuance":"DIV","nom":"M. Anthony MARY","voix":3},{"nuance":"ECO","nom":"M. Didier NORYNBERG","voix":0}]}