{"nom":"Pouzol","circ":"2ème circonscription","dpt":"Puy-de-Dôme","inscrits":226,"abs":96,"votants":130,"blancs":5,"nuls":0,"exp":125,"res":[{"nuance":"REM","nom":"M. Mohand HAMOUMOU","voix":43},{"nuance":"SOC","nom":"Mme Christine PIRÈS BEAUNE","voix":40},{"nuance":"FI","nom":"M. Pascal ESTIER","voix":11},{"nuance":"LR","nom":"Mme Stéphanie FLORI-DUTOUR","voix":11},{"nuance":"FN","nom":"M. Stanislas CHAVELET","voix":11},{"nuance":"EXG","nom":"M. Franck TRUCHON","voix":4},{"nuance":"DLF","nom":"Mme Doris VALOUR","voix":3},{"nuance":"DVG","nom":"Mme Christine BOURDIER BUISSON","voix":1},{"nuance":"DIV","nom":"M. Henri KNAUF","voix":1}]}