{"nom":"Saint-Riquier","circ":"1ère circonscription","dpt":"Somme","inscrits":926,"abs":332,"votants":594,"blancs":5,"nuls":15,"exp":574,"res":[{"nuance":"REM","nom":"M. Nicolas DUMONT","voix":221},{"nuance":"LR","nom":"M. Stéphane DECAYEUX","voix":124},{"nuance":"FI","nom":"M. François RUFFIN","voix":111},{"nuance":"FN","nom":"M. Franck DE LAPERSONNE","voix":61},{"nuance":"SOC","nom":"Mme Pascale BOISTARD","voix":30},{"nuance":"EXD","nom":"M. Yvon FLAHAUT","voix":13},{"nuance":"DLF","nom":"M. Florient TRYOEN","voix":8},{"nuance":"EXG","nom":"Mme Amal AISSAOUI","voix":3},{"nuance":"DIV","nom":"Mme Mai-Linh NGUYEN","voix":3},{"nuance":"EXG","nom":"Mme Dominique REITZMAN","voix":0},{"nuance":"DIV","nom":"M. Ricky MOUKO","voix":0}]}