{"nom":"Breilly","circ":"1ère circonscription","dpt":"Somme","inscrits":477,"abs":237,"votants":240,"blancs":2,"nuls":1,"exp":237,"res":[{"nuance":"REM","nom":"M. Nicolas DUMONT","voix":80},{"nuance":"FI","nom":"M. François RUFFIN","voix":57},{"nuance":"FN","nom":"M. Franck DE LAPERSONNE","voix":49},{"nuance":"LR","nom":"M. Stéphane DECAYEUX","voix":33},{"nuance":"SOC","nom":"Mme Pascale BOISTARD","voix":8},{"nuance":"DLF","nom":"M. Florient TRYOEN","voix":5},{"nuance":"EXG","nom":"Mme Dominique REITZMAN","voix":2},{"nuance":"EXG","nom":"Mme Amal AISSAOUI","voix":1},{"nuance":"DIV","nom":"Mme Mai-Linh NGUYEN","voix":1},{"nuance":"EXD","nom":"M. Yvon FLAHAUT","voix":1},{"nuance":"DIV","nom":"M. Ricky MOUKO","voix":0}]}