{"nom":"Pont-de-Metz","circ":"2ème circonscription","dpt":"Somme","inscrits":1631,"abs":798,"votants":833,"blancs":7,"nuls":4,"exp":822,"res":[{"nuance":"REM","nom":"Mme Barbara POMPILI","voix":392},{"nuance":"DVD","nom":"M. Olivier JARDÉ","voix":108},{"nuance":"FN","nom":"M. Nicolas VERSAEN","voix":93},{"nuance":"FI","nom":"M. Cédric MAISSE","voix":86},{"nuance":"UDI","nom":"M. Hubert DE JENLIS","voix":71},{"nuance":"SOC","nom":"M. Philippe CASIER","voix":32},{"nuance":"ECO","nom":"M. Christian GALLI","voix":21},{"nuance":"DLF","nom":"Mme Noémie DEVISSE","voix":10},{"nuance":"EXD","nom":"M. Étienne BAUVOIS","voix":8},{"nuance":"EXG","nom":"M. Bruno PALENI","voix":1},{"nuance":"DIV","nom":"M. Gérard DAULLÉ","voix":0}]}