{"nom":"Saint-Denis-lès-Bourg","circ":"1ère circonscription","dpt":"Ain","inscrits":4535,"abs":2126,"votants":2409,"blancs":28,"nuls":12,"exp":2369,"res":[{"nuance":"MDM","nom":"M. Laurent MALLET","voix":943},{"nuance":"LR","nom":"M. Xavier BRETON","voix":594},{"nuance":"SOC","nom":"Mme Florence BLATRIX-CONTAT","voix":272},{"nuance":"FN","nom":"M. Jérôme BUISSON","voix":244},{"nuance":"FI","nom":"Mme Fabrine MARTIN ZEMLIK","voix":208},{"nuance":"COM","nom":"M. Jacques FONTAINE","voix":49},{"nuance":"ECO","nom":"Mme Laurane RAIMONDO","voix":24},{"nuance":"EXG","nom":"Mme Maude LÉPAGNOT","voix":18},{"nuance":"DIV","nom":"Mme Marie CARLIER","voix":10},{"nuance":"DIV","nom":"M. Gilbert BONNOT","voix":7}]}