{"nom":"Beauregard","circ":"2ème circonscription","dpt":"Ain","inscrits":518,"abs":273,"votants":245,"blancs":3,"nuls":0,"exp":242,"res":[{"nuance":"MDM","nom":"Mme Marie Jeanne BEGUET","voix":77},{"nuance":"LR","nom":"M. Charles DE LA VERPILLIÈRE","voix":66},{"nuance":"FN","nom":"Mme Anne MICHAUD","voix":52},{"nuance":"FI","nom":"Mme Sylviane THIEBAUT","voix":22},{"nuance":"ECO","nom":"Mme Albane COLIN","voix":13},{"nuance":"DLF","nom":"Mme Pascale LEMERRE","voix":7},{"nuance":"COM","nom":"M. Guy BRULLAND","voix":4},{"nuance":"EXG","nom":"M. Vincent GOUTAGNY","voix":1},{"nuance":"DIV","nom":"M. Atila SAHIN","voix":0},{"nuance":"DIV","nom":"Mme Sandrine CHOMETTE","voix":0}]}