{"nom":"Saïx","circ":"3ème circonscription","dpt":"Tarn","inscrits":2835,"abs":1239,"votants":1596,"blancs":29,"nuls":12,"exp":1555,"res":[{"nuance":"REM","nom":"M. Jean TERLIER","voix":571},{"nuance":"FN","nom":"Mme Virginie CALLEJON","voix":290},{"nuance":"LR","nom":"M. Bernard CARAYON","voix":277},{"nuance":"FI","nom":"Mme Maud FORGEOT","voix":165},{"nuance":"SOC","nom":"Mme Linda GOURJADE","voix":145},{"nuance":"ECO","nom":"M. Stéphane DELEFORGE","voix":37},{"nuance":"COM","nom":"M. Eric JALADE","voix":25},{"nuance":"DLF","nom":"Mme Mimose RYER","voix":18},{"nuance":"ECO","nom":"M. Nicolas PINEL","voix":8},{"nuance":"ECO","nom":"Mme Virginie RIVAYRAND","voix":7},{"nuance":"EXG","nom":"Mme Chantal TRESSENS","voix":6},{"nuance":"DIV","nom":"M. Mohamed DJAFOUR","voix":5},{"nuance":"DIV","nom":"Mme Emilie CARBONELL","voix":1}]}