{"nom":"Villiers-en-Bière","circ":"1ère circonscription","dpt":"Seine-et-Marne","inscrits":166,"abs":74,"votants":92,"blancs":2,"nuls":0,"exp":90,"res":[{"nuance":"MDM","nom":"Mme Aude LUQUET","voix":26},{"nuance":"LR","nom":"M. Denis JULLEMIER","voix":24},{"nuance":"FN","nom":"Mme Stéfanie CONIGLIO","voix":12},{"nuance":"FI","nom":"Mme Bénédicte MONVILLE","voix":11},{"nuance":"SOC","nom":"M. Nicolas ALIX","voix":5},{"nuance":"EXG","nom":"M. Jean-Louis GUERRIER","voix":4},{"nuance":"DLF","nom":"Mme Léa HUGUET","voix":3},{"nuance":"DVG","nom":"Mme Malika HADBI","voix":2},{"nuance":"DVD","nom":"M. Franck VEZILIER","voix":2},{"nuance":"DVD","nom":"Mme Nathalie BEAULNES-SERENI","voix":1},{"nuance":"DVD","nom":"Mme Bénédicte SAVATIER","voix":0},{"nuance":"DIV","nom":"Mme Catherine GALLOIS","voix":0},{"nuance":"EXG","nom":"M. Patrick DELVERT","voix":0},{"nuance":"DIV","nom":"M. Flavien ATSE","voix":0},{"nuance":"DVD","nom":"M. Henri Komivi DJOLEGBEHOU","voix":0},{"nuance":"COM","nom":"M. Yves REMY","voix":0},{"nuance":"DIV","nom":"M. Najib AZRGUI","voix":0}]}