{"nom":"Colmey","circ":"3ème circonscription","dpt":"Meurthe-et-Moselle","inscrits":186,"abs":105,"votants":81,"blancs":0,"nuls":0,"exp":81,"res":[{"nuance":"REM","nom":"M. Xavier PALUSZKIEWICZ","voix":26},{"nuance":"LR","nom":"M. Mathieu SERVAGI","voix":19},{"nuance":"FN","nom":"Mme Céline DOLCEMASCOLO","voix":18},{"nuance":"SOC","nom":"M. Christian ECKERT","voix":7},{"nuance":"FI","nom":"M. Patrice ZOLFO","voix":6},{"nuance":"DVD","nom":"M. Didier SUARDI","voix":2},{"nuance":"ECO","nom":"M. Mikaël AGOPIANTZ","voix":1},{"nuance":"EXG","nom":"Mme Annick JOLIVET","voix":1},{"nuance":"DLF","nom":"Mme Christiane VAUTRIN","voix":1},{"nuance":"DIV","nom":"Mme Cécile GIRARDET","voix":0},{"nuance":"COM","nom":"M. Jean-Marc LEON","voix":0},{"nuance":"DVD","nom":"M. Arnaud LE NENAN","voix":0},{"nuance":"DVD","nom":"Mme Sonia SADOUNE","voix":0},{"nuance":"EXG","nom":"M. Pierre LUX","voix":0},{"nuance":"DIV","nom":"M. Walter DI LUIGI","voix":0}]}