{"nom":"Soucy","circ":"3ème circonscription","dpt":"Yonne","inscrits":1237,"abs":629,"votants":608,"blancs":10,"nuls":3,"exp":595,"res":[{"nuance":"FN","nom":"M. Julien ODOUL","voix":186},{"nuance":"REM","nom":"Mme Michèle CROUZET","voix":177},{"nuance":"LR","nom":"Mme Clarisse QUENTIN","voix":74},{"nuance":"FI","nom":"Mme Isabelle MICHAUD","voix":41},{"nuance":"DVD","nom":"Mme Delphine GREMY","voix":37},{"nuance":"SOC","nom":"M. Dominique BOURREAU","voix":28},{"nuance":"COM","nom":"M. Patrick BLIN","voix":17},{"nuance":"DLF","nom":"M. Sylvain SIFFLET-LAFAVERGE","voix":13},{"nuance":"DVD","nom":"M. Xavier POINSARD","voix":7},{"nuance":"ECO","nom":"M. Bernard BEHEREC","voix":6},{"nuance":"EXG","nom":"Mme Simonne PALLANT","voix":5},{"nuance":"DVG","nom":"M. Olivier MARTIN","voix":2},{"nuance":"DIV","nom":"Mme Muslimé SUNAR","voix":1},{"nuance":"DIV","nom":"Mme Isabelle CORRADO","voix":1},{"nuance":"DIV","nom":"M. Jean-Baptiste DUFAY","voix":0}]}