{"nom":"Rouvres-sous-Meilly","circ":"5ème circonscription","dpt":"Côte-d'Or","inscrits":90,"abs":39,"votants":51,"blancs":1,"nuls":0,"exp":50,"res":[{"nuance":"REM","nom":"M. Didier PARIS","voix":20},{"nuance":"LR","nom":"M. Hubert POULLOT","voix":11},{"nuance":"FN","nom":"M. René LIORET","voix":7},{"nuance":"FI","nom":"Mme Elisabeth KREMER","voix":4},{"nuance":"SOC","nom":"M. Jérôme FLACHE","voix":3},{"nuance":"ECO","nom":"Mme Carole BERNHARD","voix":3},{"nuance":"EXG","nom":"Mme Françoise PETET","voix":1},{"nuance":"ECO","nom":"M. Patrick MULLER","voix":1},{"nuance":"COM","nom":"M. Jacques CARDOT","voix":0},{"nuance":"DIV","nom":"M. Edouard CLAIR","voix":0}]}