{"nom":"Saint-Michel","circ":"3ème circonscription","dpt":"Aisne","inscrits":2318,"abs":1360,"votants":958,"blancs":15,"nuls":11,"exp":932,"res":[{"nuance":"FN","nom":"M. Paul-Henry HANSEN-CATTA","voix":316},{"nuance":"SOC","nom":"M. Jean-Louis BRICOUT","voix":210},{"nuance":"MDM","nom":"M. Alain HUSILLOS-CRESPO","voix":152},{"nuance":"FI","nom":"Mme Alexandra MORTET","voix":105},{"nuance":"LR","nom":"M. Laurent MARLOT","voix":81},{"nuance":"ECO","nom":"M. Christophe PARENT","voix":20},{"nuance":"DLF","nom":"M. Philippe TORRE","voix":20},{"nuance":"COM","nom":"M. Aurélien GALL","voix":16},{"nuance":"DIV","nom":"Mme Clémence THÉRY-HERMAIN","voix":7},{"nuance":"EXG","nom":"Mme Laetitia VOISIN","voix":5}]}