{"nom":"Salses-le-Château","circ":"2ème circonscription","dpt":"Pyrénées-Orientales","inscrits":2246,"abs":1078,"votants":1168,"blancs":31,"nuls":12,"exp":1125,"res":[{"nuance":"FN","nom":"M. Louis ALIOT","voix":351},{"nuance":"MDM","nom":"Mme Christine ESPERT","voix":291},{"nuance":"LR","nom":"M. Fernand SIRÉ","voix":138},{"nuance":"FI","nom":"Mme Catherine DAVID","voix":132},{"nuance":"SOC","nom":"Mme Marie-Pierre SADOURNY","voix":70},{"nuance":"COM","nom":"M. Pascal EGIDO","voix":38},{"nuance":"REG","nom":"M. Alexis ABAT","voix":31},{"nuance":"EXG","nom":"M. Liberto PLANA","voix":17},{"nuance":"REG","nom":"M. Laurent PERRIE","voix":14},{"nuance":"DLF","nom":"Mme Solange RODIER","voix":13},{"nuance":"ECO","nom":"Mme Bérengère BATAILLER","voix":12},{"nuance":"DIV","nom":"M. Patrick RAMIREZ","voix":7},{"nuance":"ECO","nom":"M. Dominique LABIS","voix":6},{"nuance":"DIV","nom":"M. Michel ROIG","voix":5}]}