{"nom":"Gençay","circ":"3ème circonscription","dpt":"Vienne","inscrits":1333,"abs":645,"votants":688,"blancs":11,"nuls":8,"exp":669,"res":[{"nuance":"REM","nom":"M. Jean-Michel CLÉMENT","voix":302},{"nuance":"LR","nom":"M. Enguerrand DELANNOY","voix":88},{"nuance":"FI","nom":"Mme Marie-José CELLOT","voix":79},{"nuance":"FN","nom":"Mme Delphine JUMEAU","voix":69},{"nuance":"DVD","nom":"M. Gérard HERBERT","voix":42},{"nuance":"COM","nom":"Mme Valérie LAFOY","voix":31},{"nuance":"ECO","nom":"M. Florian SÉJOURNÉ","voix":20},{"nuance":"DVG","nom":"M. Thierry MESMIN","voix":19},{"nuance":"EXG","nom":"Mme Danièle CASSETTE","voix":9},{"nuance":"DVD","nom":"M. Aymeric MAÎTRE DU CHAMBON","voix":6},{"nuance":"DIV","nom":"M. Didier HENRY","voix":3},{"nuance":"DIV","nom":"M. Christophe GRESELIN","voix":1}]}