{"nom":"Jeufosse","circ":"9ème circonscription","dpt":"Yvelines","inscrits":363,"abs":178,"votants":185,"blancs":2,"nuls":1,"exp":182,"res":[{"nuance":"MDM","nom":"M. Bruno MILLIENNE","voix":67},{"nuance":"FN","nom":"M. Emmanuel NORBERT-COUADE","voix":49},{"nuance":"LR","nom":"M. Jean-Marie TETART","voix":36},{"nuance":"FI","nom":"M. Guillaume QUINTIN","voix":15},{"nuance":"DLF","nom":"Mme Marie-France LAVENNE-REYNAERT","voix":6},{"nuance":"DVD","nom":"M. Ferid HAMDI","voix":3},{"nuance":"ECO","nom":"M. Salah ANOUAR","voix":2},{"nuance":"EXD","nom":"Mme Christiane GADÉ","voix":2},{"nuance":"EXG","nom":"Mme Victoria CHAKARIAN","voix":1},{"nuance":"DVD","nom":"M. François MARTIN","voix":1},{"nuance":"DIV","nom":"Mme Isabelle BEGUE","voix":0},{"nuance":"DVD","nom":"M. Renaud LATAILLADE","voix":0},{"nuance":"ECO","nom":"M. Nadir Yanisse MALLEM","voix":0},{"nuance":"SOC","nom":"M. Ali MOHAMMAD","voix":0},{"nuance":"COM","nom":"M. Thibaud DE FLEURY","voix":0},{"nuance":"EXG","nom":"M. Philippe GOMMARD","voix":0}]}