{"nom":"Schwobsheim","circ":"5ème circonscription","dpt":"Bas-Rhin","inscrits":229,"abs":91,"votants":138,"blancs":1,"nuls":0,"exp":137,"res":[{"nuance":"REG","nom":"M. Gérard SIMLER","voix":71},{"nuance":"LR","nom":"M. Antoine HERTH","voix":32},{"nuance":"FN","nom":"Mme Eliane KLEIN","voix":21},{"nuance":"EXG","nom":"M. Patrick DUTTER","voix":3},{"nuance":"ECO","nom":"Mme Caroline REYS","voix":3},{"nuance":"ECO","nom":"M. Daniel WEBER","voix":2},{"nuance":"DIV","nom":"Mme Candice VETROFF","voix":2},{"nuance":"ECO","nom":"M. Christian DANTZ","voix":1},{"nuance":"DLF","nom":"Mme Christine BECCARI","voix":1},{"nuance":"FI","nom":"Mme Janig TERRIER","voix":1},{"nuance":"COM","nom":"Mme Christine ROMANUS","voix":0},{"nuance":"DIV","nom":"M. Feridun ULUSOY","voix":0},{"nuance":"DIV","nom":"M. Eric LAPP-LAUTH","voix":0},{"nuance":"EXD","nom":"M. Eric GAUTIER","voix":0}]}