{"nom":"Griesheim-sur-Souffel","circ":"4ème circonscription","dpt":"Bas-Rhin","inscrits":963,"abs":413,"votants":550,"blancs":4,"nuls":0,"exp":546,"res":[{"nuance":"REM","nom":"Mme Martine WONNER","voix":283},{"nuance":"LR","nom":"Mme Sophie ROHFRITSCH","voix":113},{"nuance":"FN","nom":"M. Thibault MANTEAUX","voix":43},{"nuance":"REG","nom":"Mme Morgane KECK","voix":29},{"nuance":"FI","nom":"M. Albert SCHWARTZ","voix":24},{"nuance":"ECO","nom":"Mme Nathalie PALMIER","voix":23},{"nuance":"DLF","nom":"M. Eric MOUY","voix":6},{"nuance":"DIV","nom":"Mme Alexandra BRASLERET","voix":5},{"nuance":"EXD","nom":"M. Jacques CORDONNIER","voix":5},{"nuance":"ECO","nom":"Mme Michèle TREMOLIERES","voix":5},{"nuance":"RDG","nom":"M. Thibaut VINCI","voix":4},{"nuance":"COM","nom":"Mme Yasmina CHADLI","voix":3},{"nuance":"DIV","nom":"M. Patrick ARBOGAST","voix":2},{"nuance":"EXG","nom":"M. Marc BAUD-BERTHIER","voix":1},{"nuance":"EXG","nom":"M. Mathieu LE TALLEC","voix":0}]}